app/__init__.py
app/main.py
app/utils/__init__.py
app/utils/helpers/__init__.py
app/utils/helpers/logging.py
create_quas_app-0.5.5.dist-info/METADATA
create_quas_app-0.5.5.dist-info/WHEEL
create_quas_app-0.5.5.dist-info/entry_points.txt
create_quas_app-0.5.5.dist-info/top_level.txt
create_quas_app-0.5.5.dist-info/RECORD
