Metadata-Version: 2.1
Name: create-quas-app
Version: 0.5.5
Summary: A basic Quick API Setup using Flask, intended for rapid project initiation.
Home-page: https://github.com/zeddyemy/QUAS
Author: Emmanuel Esho
Requires-Dist: Click
